{
  "conformsTo": "https://project-open-data.cio.gov/v1.1/schema",
  "dataset": [
{"accessLevel":"public","landingPage":"https://data.weho.org/d/twt6-v6gc","issued":"2015-11-09","modified":"2015-11-09","contactPoint":{"fn":"<Nobody>","hasEmail":"mailto:"},"identifier":"https://data.weho.org/api/views/twt6-v6gc","publisher":{"name":"data.weho.org"},"description":"Urban Art Locations","title":"Urban Art Locations","distribution":[{"downloadURL":"https://data.weho.org/api/views/twt6-v6gc/rows.csv?accessType=DOWNLOAD","mediaType":"text/csv"},{"downloadURL":"https://data.weho.org/api/views/twt6-v6gc/rows.rdf?accessType=DOWNLOAD","mediaType":"application/rdf+xml"},{"downloadURL":"https://data.weho.org/api/views/twt6-v6gc/rows.json?accessType=DOWNLOAD","mediaType":"application/json"},{"downloadURL":"https://data.weho.org/api/views/twt6-v6gc/rows.xml?accessType=DOWNLOAD","mediaType":"application/xml"}],"theme":["Art"]},{"accessLevel":"public","landingPage":"https://data.weho.org/d/u68a-wdk5","issued":"2015-11-03","modified":"2015-11-03","contactPoint":{"fn":"<Nobody>","hasEmail":"mailto:"},"identifier":"https://data.weho.org/api/views/u68a-wdk5","publisher":{"name":"data.weho.org"},"description":"2015 Special Event Permits","title":"2015 Special Event Permits","distribution":[{"downloadURL":"https://data.weho.org/api/views/u68a-wdk5/rows.csv?accessType=DOWNLOAD","mediaType":"text/csv"},{"downloadURL":"https://data.weho.org/api/views/u68a-wdk5/rows.rdf?accessType=DOWNLOAD","mediaType":"application/rdf+xml"},{"downloadURL":"https://data.weho.org/api/views/u68a-wdk5/rows.json?accessType=DOWNLOAD","mediaType":"application/json"},{"downloadURL":"https://data.weho.org/api/views/u68a-wdk5/rows.xml?accessType=DOWNLOAD","mediaType":"application/xml"}],"theme":["Special Events"]},{"accessLevel":"public","landingPage":"https://data.weho.org/d/xd5y-dzvf","issued":"2015-11-03","modified":"2015-11-03","contactPoint":{"fn":"<Nobody>","hasEmail":"mailto:"},"identifier":"https://data.weho.org/api/views/xd5y-dzvf","publisher":{"name":"data.weho.org"},"description":"WeHo Filming Activity","title":"WeHo Filming Activity","distribution":[{"downloadURL":"https://data.weho.org/api/views/xd5y-dzvf/rows.csv?accessType=DOWNLOAD","mediaType":"text/csv"},{"downloadURL":"https://data.weho.org/api/views/xd5y-dzvf/rows.rdf?accessType=DOWNLOAD","mediaType":"application/rdf+xml"},{"downloadURL":"https://data.weho.org/api/views/xd5y-dzvf/rows.json?accessType=DOWNLOAD","mediaType":"application/json"},{"downloadURL":"https://data.weho.org/api/views/xd5y-dzvf/rows.xml?accessType=DOWNLOAD","mediaType":"application/xml"}],"theme":["Filming"]},{"accessLevel":"public","landingPage":"https://data.weho.org/d/dtgh-gvxt","issued":"2015-09-08","modified":"2015-09-08","contactPoint":{"fn":"<Nobody>","hasEmail":"mailto:"},"identifier":"https://data.weho.org/api/views/dtgh-gvxt","publisher":{"name":"data.weho.org"},"description":"The following list of residential units has been provided to the Department of Rent Stabilization by the owners or their representatives, who have indicated that they are available for rent. As a service to its constituents, the Department is making the list available to tenants seeking rental units. Neither the department nor the city of west hollywood makes any representation whatsoever about the units, including their condition, status and the terms of any rental agreement.\r\n \r\nTenants interested in renting these units should conduct their own inquiries and investigations before entering into a rental agreement.","title":"Residential Rental Referral List","distribution":[{"downloadURL":"https://data.weho.org/api/views/dtgh-gvxt/rows.csv?accessType=DOWNLOAD","mediaType":"text/csv"},{"downloadURL":"https://data.weho.org/api/views/dtgh-gvxt/rows.rdf?accessType=DOWNLOAD","mediaType":"application/rdf+xml"},{"downloadURL":"https://data.weho.org/api/views/dtgh-gvxt/rows.json?accessType=DOWNLOAD","mediaType":"application/json"},{"downloadURL":"https://data.weho.org/api/views/dtgh-gvxt/rows.xml?accessType=DOWNLOAD","mediaType":"application/xml"}],"theme":["Housing"]},{"accessLevel":"public","landingPage":"https://data.weho.org/d/tb7r-wt2t","issued":"2015-08-13","modified":"2015-08-20","contactPoint":{"fn":"<Nobody>","hasEmail":"mailto:"},"identifier":"https://data.weho.org/api/views/tb7r-wt2t","publisher":{"name":"data.weho.org"},"description":"This is only test data. Please ignore.","title":"TEST Garbage Collection Schedule","distribution":[{"downloadURL":"https://data.weho.org/api/views/tb7r-wt2t/rows.csv?accessType=DOWNLOAD","mediaType":"text/csv"},{"downloadURL":"https://data.weho.org/api/views/tb7r-wt2t/rows.rdf?accessType=DOWNLOAD","mediaType":"application/rdf+xml"},{"downloadURL":"https://data.weho.org/api/views/tb7r-wt2t/rows.json?accessType=DOWNLOAD","mediaType":"application/json"},{"downloadURL":"https://data.weho.org/api/views/tb7r-wt2t/rows.xml?accessType=DOWNLOAD","mediaType":"application/xml"}]},{"accessLevel":"public","landingPage":"https://data.weho.org/d/nuhk-wpiu","issued":"2015-06-14","modified":"2015-08-20","contactPoint":{"fn":"<Nobody>","hasEmail":"mailto:"},"identifier":"https://data.weho.org/api/views/nuhk-wpiu","publisher":{"name":"data.weho.org"},"description":"This dataset contains location information as well as descriptions for the fiscal year 2014 - 2019 Capital Improvement Project budget","title":"2014-19 CIP Locations and Descriptions","distribution":[{"downloadURL":"https://data.weho.org/api/views/nuhk-wpiu/rows.csv?accessType=DOWNLOAD","mediaType":"text/csv"},{"downloadURL":"https://data.weho.org/api/views/nuhk-wpiu/rows.rdf?accessType=DOWNLOAD","mediaType":"application/rdf+xml"},{"downloadURL":"https://data.weho.org/api/views/nuhk-wpiu/rows.json?accessType=DOWNLOAD","mediaType":"application/json"},{"downloadURL":"https://data.weho.org/api/views/nuhk-wpiu/rows.xml?accessType=DOWNLOAD","mediaType":"application/xml"}],"theme":["CIP"]},{"accessLevel":"public","landingPage":"https://data.weho.org/d/iich-5dk8","issued":"2015-06-14","modified":"2015-08-20","contactPoint":{"fn":"<Nobody>","hasEmail":"mailto:"},"identifier":"https://data.weho.org/api/views/iich-5dk8","publisher":{"name":"data.weho.org"},"description":"This dataset contains summary information for the fiscal year 2014 - 2019 Capital Improvement Project budget","title":"2014-19 Five Year Capital Work Plan","distribution":[{"downloadURL":"https://data.weho.org/api/views/iich-5dk8/rows.csv?accessType=DOWNLOAD","mediaType":"text/csv"},{"downloadURL":"https://data.weho.org/api/views/iich-5dk8/rows.rdf?accessType=DOWNLOAD","mediaType":"application/rdf+xml"},{"downloadURL":"https://data.weho.org/api/views/iich-5dk8/rows.json?accessType=DOWNLOAD","mediaType":"application/json"},{"downloadURL":"https://data.weho.org/api/views/iich-5dk8/rows.xml?accessType=DOWNLOAD","mediaType":"application/xml"}],"theme":["CIP"]},{"accessLevel":"public","landingPage":"https://data.weho.org/d/c3hb-db2f","issued":"2015-06-04","modified":"2015-08-20","contactPoint":{"fn":"<Nobody>","hasEmail":"mailto:"},"identifier":"https://data.weho.org/api/views/c3hb-db2f","publisher":{"name":"data.weho.org"},"description":"This dataset contains the line-item detail for the 2013-16 revenue budget","title":"Budget Revenue Detail FY13-16","distribution":[{"downloadURL":"https://data.weho.org/api/views/c3hb-db2f/rows.csv?accessType=DOWNLOAD","mediaType":"text/csv"},{"downloadURL":"https://data.weho.org/api/views/c3hb-db2f/rows.rdf?accessType=DOWNLOAD","mediaType":"application/rdf+xml"},{"downloadURL":"https://data.weho.org/api/views/c3hb-db2f/rows.json?accessType=DOWNLOAD","mediaType":"application/json"},{"downloadURL":"https://data.weho.org/api/views/c3hb-db2f/rows.xml?accessType=DOWNLOAD","mediaType":"application/xml"}],"theme":["Revenues"]},{"accessLevel":"public","landingPage":"https://data.weho.org/d/xxix-2i77","issued":"2015-06-04","modified":"2015-08-20","contactPoint":{"fn":"<Nobody>","hasEmail":"mailto:"},"identifier":"https://data.weho.org/api/views/xxix-2i77","publisher":{"name":"data.weho.org"},"description":"This dataset contains the line-item detail for the 2013-16 expenditure budget","title":"Budget Expenditure Detail FY13-16","distribution":[{"downloadURL":"https://data.weho.org/api/views/xxix-2i77/rows.csv?accessType=DOWNLOAD","mediaType":"text/csv"},{"downloadURL":"https://data.weho.org/api/views/xxix-2i77/rows.rdf?accessType=DOWNLOAD","mediaType":"application/rdf+xml"},{"downloadURL":"https://data.weho.org/api/views/xxix-2i77/rows.json?accessType=DOWNLOAD","mediaType":"application/json"},{"downloadURL":"https://data.weho.org/api/views/xxix-2i77/rows.xml?accessType=DOWNLOAD","mediaType":"application/xml"}],"theme":["Expenditures"]},{"accessLevel":"public","landingPage":"https://data.weho.org/d/fiyy-83j4","issued":"2014-10-20","modified":"2015-08-20","contactPoint":{"fn":"<Nobody>","hasEmail":"mailto:"},"identifier":"https://data.weho.org/api/views/fiyy-83j4","publisher":{"name":"data.weho.org"},"description":"View listing of the City’s parking garages, lots and public valet stations.","title":"Public Parking","distribution":[{"downloadURL":"https://data.weho.org/api/views/fiyy-83j4/rows.csv?accessType=DOWNLOAD","mediaType":"text/csv"},{"downloadURL":"https://data.weho.org/api/views/fiyy-83j4/rows.rdf?accessType=DOWNLOAD","mediaType":"application/rdf+xml"},{"downloadURL":"https://data.weho.org/api/views/fiyy-83j4/rows.json?accessType=DOWNLOAD","mediaType":"application/json"},{"downloadURL":"https://data.weho.org/api/views/fiyy-83j4/rows.xml?accessType=DOWNLOAD","mediaType":"application/xml"}],"theme":["Parking"]},{"accessLevel":"public","landingPage":"https://data.weho.org/d/atdr-sk64","issued":"2014-09-22","modified":"2015-08-20","contactPoint":{"fn":"<Nobody>","hasEmail":"mailto:"},"identifier":"https://data.weho.org/api/views/atdr-sk64","publisher":{"name":"data.weho.org"},"description":"This dataset contains active City contracts as of September 22, 2014. The following are the contract types: franch = Franchise Agreements, grants = City Grants, graphic&pr\t= Graphic Artist, profsvcs = Professional & Contract Services, pworks = Public Works & Construction, recreation\t= Recreation Services, specevents = Special Event Related Services, and web/tech = Information Technology Related Services","title":"Active Contracts","distribution":[{"downloadURL":"https://data.weho.org/api/views/atdr-sk64/rows.csv?accessType=DOWNLOAD","mediaType":"text/csv"},{"downloadURL":"https://data.weho.org/api/views/atdr-sk64/rows.rdf?accessType=DOWNLOAD","mediaType":"application/rdf+xml"},{"downloadURL":"https://data.weho.org/api/views/atdr-sk64/rows.json?accessType=DOWNLOAD","mediaType":"application/json"},{"downloadURL":"https://data.weho.org/api/views/atdr-sk64/rows.xml?accessType=DOWNLOAD","mediaType":"application/xml"}],"theme":["Contracts"]},{"accessLevel":"public","landingPage":"https://data.weho.org/d/5p2f-z8xv","issued":"2014-07-18","modified":"2015-08-20","contactPoint":{"fn":"<Nobody>","hasEmail":"mailto:"},"identifier":"https://data.weho.org/api/views/5p2f-z8xv","publisher":{"name":"data.weho.org"},"description":"Active Regulatory Licenses","title":"Active Regulatory Licenses","distribution":[{"downloadURL":"https://data.weho.org/api/views/5p2f-z8xv/rows.csv?accessType=DOWNLOAD","mediaType":"text/csv"},{"downloadURL":"https://data.weho.org/api/views/5p2f-z8xv/rows.rdf?accessType=DOWNLOAD","mediaType":"application/rdf+xml"},{"downloadURL":"https://data.weho.org/api/views/5p2f-z8xv/rows.json?accessType=DOWNLOAD","mediaType":"application/json"},{"downloadURL":"https://data.weho.org/api/views/5p2f-z8xv/rows.xml?accessType=DOWNLOAD","mediaType":"application/xml"}],"theme":["Business"]},{"accessLevel":"public","landingPage":"https://data.weho.org/d/g47c-h4yt","issued":"2014-07-15","modified":"2015-08-20","contactPoint":{"fn":"<Nobody>","hasEmail":"mailto:"},"identifier":"https://data.weho.org/api/views/g47c-h4yt","publisher":{"name":"data.weho.org"},"description":"One of the City's ongoing strategic programs is to control traffic volumes, decrease traffic speeds and create safer walking and bicycling conditions.  In an effort to do this, the City regularly surveys traffic conditions.   This dataset contains the City's most recent traffic volume data.","title":"Citywide Traffic Volumes","distribution":[{"downloadURL":"https://data.weho.org/api/views/g47c-h4yt/rows.csv?accessType=DOWNLOAD","mediaType":"text/csv"},{"downloadURL":"https://data.weho.org/api/views/g47c-h4yt/rows.rdf?accessType=DOWNLOAD","mediaType":"application/rdf+xml"},{"downloadURL":"https://data.weho.org/api/views/g47c-h4yt/rows.json?accessType=DOWNLOAD","mediaType":"application/json"},{"downloadURL":"https://data.weho.org/api/views/g47c-h4yt/rows.xml?accessType=DOWNLOAD","mediaType":"application/xml"}],"theme":["Traffic"]}  ]
}
