{
  "conformsTo": "https://project-open-data.cio.gov/v1.1/schema",
  "dataset": [
{"accessLevel":"public","landingPage":"https://performance.danvilleva.gov/d/f8qq-ugyy","issued":"2015-10-23","modified":"2015-10-23","contactPoint":{"fn":"<Nobody>","hasEmail":"mailto:"},"keyword":["motor vehicle theft","car theft"],"identifier":"https://performance.danvilleva.gov/api/views/f8qq-ugyy","publisher":{"name":"performance.danvilleva.gov"},"description":"Number of motor vehicle thefts in the City of Danville by calendar year","title":"Property Crimes - Motor Vehicle Theft","distribution":[{"downloadURL":"https://performance.danvilleva.gov/api/views/f8qq-ugyy/rows.csv?accessType=DOWNLOAD","mediaType":"text/csv"},{"downloadURL":"https://performance.danvilleva.gov/api/views/f8qq-ugyy/rows.rdf?accessType=DOWNLOAD","mediaType":"application/rdf+xml"},{"downloadURL":"https://performance.danvilleva.gov/api/views/f8qq-ugyy/rows.json?accessType=DOWNLOAD","mediaType":"application/json"},{"downloadURL":"https://performance.danvilleva.gov/api/views/f8qq-ugyy/rows.xml?accessType=DOWNLOAD","mediaType":"application/xml"}]},{"accessLevel":"public","landingPage":"https://performance.danvilleva.gov/d/5cyg-45x7","issued":"2015-10-23","modified":"2015-10-23","contactPoint":{"fn":"<Nobody>","hasEmail":"mailto:"},"identifier":"https://performance.danvilleva.gov/api/views/5cyg-45x7","publisher":{"name":"performance.danvilleva.gov"},"description":"Arson figures by calendar year in the City of Danville.","title":"Property Crimes - Arson","distribution":[{"downloadURL":"https://performance.danvilleva.gov/api/views/5cyg-45x7/rows.csv?accessType=DOWNLOAD","mediaType":"text/csv"},{"downloadURL":"https://performance.danvilleva.gov/api/views/5cyg-45x7/rows.rdf?accessType=DOWNLOAD","mediaType":"application/rdf+xml"},{"downloadURL":"https://performance.danvilleva.gov/api/views/5cyg-45x7/rows.json?accessType=DOWNLOAD","mediaType":"application/json"},{"downloadURL":"https://performance.danvilleva.gov/api/views/5cyg-45x7/rows.xml?accessType=DOWNLOAD","mediaType":"application/xml"}]},{"accessLevel":"public","landingPage":"https://performance.danvilleva.gov/d/yhes-5s8j","issued":"2015-10-23","modified":"2015-10-23","contactPoint":{"fn":"<Nobody>","hasEmail":"mailto:"},"keyword":["larceny","larcenies"],"identifier":"https://performance.danvilleva.gov/api/views/yhes-5s8j","publisher":{"name":"performance.danvilleva.gov"},"description":"Number of larcenies in the City of Danville by calendar year","title":"Property Crimes - Larceny","distribution":[{"downloadURL":"https://performance.danvilleva.gov/api/views/yhes-5s8j/rows.csv?accessType=DOWNLOAD","mediaType":"text/csv"},{"downloadURL":"https://performance.danvilleva.gov/api/views/yhes-5s8j/rows.rdf?accessType=DOWNLOAD","mediaType":"application/rdf+xml"},{"downloadURL":"https://performance.danvilleva.gov/api/views/yhes-5s8j/rows.json?accessType=DOWNLOAD","mediaType":"application/json"},{"downloadURL":"https://performance.danvilleva.gov/api/views/yhes-5s8j/rows.xml?accessType=DOWNLOAD","mediaType":"application/xml"}]},{"accessLevel":"public","landingPage":"https://performance.danvilleva.gov/d/qecq-g9cg","issued":"2015-10-23","modified":"2015-10-23","contactPoint":{"fn":"<Nobody>","hasEmail":"mailto:"},"keyword":["burglary"],"identifier":"https://performance.danvilleva.gov/api/views/qecq-g9cg","publisher":{"name":"performance.danvilleva.gov"},"description":"Number of burglaries in the City of Danville by calendar year","title":"Property Crimes - Burglary","distribution":[{"downloadURL":"https://performance.danvilleva.gov/api/views/qecq-g9cg/rows.csv?accessType=DOWNLOAD","mediaType":"text/csv"},{"downloadURL":"https://performance.danvilleva.gov/api/views/qecq-g9cg/rows.rdf?accessType=DOWNLOAD","mediaType":"application/rdf+xml"},{"downloadURL":"https://performance.danvilleva.gov/api/views/qecq-g9cg/rows.json?accessType=DOWNLOAD","mediaType":"application/json"},{"downloadURL":"https://performance.danvilleva.gov/api/views/qecq-g9cg/rows.xml?accessType=DOWNLOAD","mediaType":"application/xml"}]},{"accessLevel":"public","landingPage":"https://performance.danvilleva.gov/d/cyse-nc7i","issued":"2015-10-23","modified":"2015-10-23","contactPoint":{"fn":"<Nobody>","hasEmail":"mailto:"},"identifier":"https://performance.danvilleva.gov/api/views/cyse-nc7i","publisher":{"name":"performance.danvilleva.gov"},"description":"A look at a subset of the property crime rate in the City of Danville, VA. This figure is based on the data for larcenies and burglaries.","title":"Property Crime Rate","distribution":[{"downloadURL":"https://performance.danvilleva.gov/api/views/cyse-nc7i/rows.csv?accessType=DOWNLOAD","mediaType":"text/csv"},{"downloadURL":"https://performance.danvilleva.gov/api/views/cyse-nc7i/rows.rdf?accessType=DOWNLOAD","mediaType":"application/rdf+xml"},{"downloadURL":"https://performance.danvilleva.gov/api/views/cyse-nc7i/rows.json?accessType=DOWNLOAD","mediaType":"application/json"},{"downloadURL":"https://performance.danvilleva.gov/api/views/cyse-nc7i/rows.xml?accessType=DOWNLOAD","mediaType":"application/xml"}]},{"accessLevel":"public","landingPage":"https://performance.danvilleva.gov/d/4y4c-z8ye","issued":"2015-10-23","modified":"2015-10-23","contactPoint":{"fn":"<Nobody>","hasEmail":"mailto:"},"keyword":["robbery","robberies","violent crime"],"identifier":"https://performance.danvilleva.gov/api/views/4y4c-z8ye","publisher":{"name":"performance.danvilleva.gov"},"description":"Number of robberies in the City of Danville by calendar year.","title":"Violent Crimes - Robbery","distribution":[{"downloadURL":"https://performance.danvilleva.gov/api/views/4y4c-z8ye/rows.csv?accessType=DOWNLOAD","mediaType":"text/csv"},{"downloadURL":"https://performance.danvilleva.gov/api/views/4y4c-z8ye/rows.rdf?accessType=DOWNLOAD","mediaType":"application/rdf+xml"},{"downloadURL":"https://performance.danvilleva.gov/api/views/4y4c-z8ye/rows.json?accessType=DOWNLOAD","mediaType":"application/json"},{"downloadURL":"https://performance.danvilleva.gov/api/views/4y4c-z8ye/rows.xml?accessType=DOWNLOAD","mediaType":"application/xml"}]},{"accessLevel":"public","landingPage":"https://performance.danvilleva.gov/d/66bz-bjpe","issued":"2015-10-23","modified":"2015-10-23","contactPoint":{"fn":"<Nobody>","hasEmail":"mailto:"},"identifier":"https://performance.danvilleva.gov/api/views/66bz-bjpe","publisher":{"name":"performance.danvilleva.gov"},"description":"Number of rapes in the City of Danville by calendar year.","title":"Violent Crimes - Rape","distribution":[{"downloadURL":"https://performance.danvilleva.gov/api/views/66bz-bjpe/rows.csv?accessType=DOWNLOAD","mediaType":"text/csv"},{"downloadURL":"https://performance.danvilleva.gov/api/views/66bz-bjpe/rows.rdf?accessType=DOWNLOAD","mediaType":"application/rdf+xml"},{"downloadURL":"https://performance.danvilleva.gov/api/views/66bz-bjpe/rows.json?accessType=DOWNLOAD","mediaType":"application/json"},{"downloadURL":"https://performance.danvilleva.gov/api/views/66bz-bjpe/rows.xml?accessType=DOWNLOAD","mediaType":"application/xml"}]},{"accessLevel":"public","landingPage":"https://performance.danvilleva.gov/d/j7fw-vchi","issued":"2015-03-05","modified":"2015-03-05","contactPoint":{"fn":"<Nobody>","hasEmail":"mailto:"},"identifier":"https://performance.danvilleva.gov/api/views/j7fw-vchi","publisher":{"name":"performance.danvilleva.gov"},"description":"Grant Funding for the Danville Police Department","title":"Grant Funding 2005-2014","distribution":[{"downloadURL":"https://performance.danvilleva.gov/api/views/j7fw-vchi/rows.csv?accessType=DOWNLOAD","mediaType":"text/csv"},{"downloadURL":"https://performance.danvilleva.gov/api/views/j7fw-vchi/rows.rdf?accessType=DOWNLOAD","mediaType":"application/rdf+xml"},{"downloadURL":"https://performance.danvilleva.gov/api/views/j7fw-vchi/rows.json?accessType=DOWNLOAD","mediaType":"application/json"},{"downloadURL":"https://performance.danvilleva.gov/api/views/j7fw-vchi/rows.xml?accessType=DOWNLOAD","mediaType":"application/xml"}]}  ]
}
